pyvisauto/__init__.py
pyvisauto/main.py
pyvisauto-1.0.3.dist-info/LICENSE
pyvisauto-1.0.3.dist-info/METADATA
pyvisauto-1.0.3.dist-info/WHEEL
pyvisauto-1.0.3.dist-info/top_level.txt
pyvisauto-1.0.3.dist-info/RECORD
