Metadata-Version: 2.1
Name: pyvisauto
Version: 1.0.3
Summary: pyvisauto - a vision-based automation tool
Home-page: https://github.com/mrmin123/pyvisauto
Author: Minyoung Choi
Author-email: minyoung.choi@gmail.com
License: UNKNOWN
Platform: UNKNOWN
Classifier: Programming Language :: Python :: 3
Classifier: License :: OSI Approved :: GNU General Public License v3 or later (GPLv3+)
Classifier: Operating System :: OS Independent
Requires-Python: >=3.4.*, <3.8
Requires-Dist: opencv-contrib-python-headless (~=4.1.2.30)
Requires-Dist: pillow (~=7.2.0)
Requires-Dist: pyautogui (~=0.9.48)
Requires-Dist: pytesseract (~=0.3.0)
Requires-Dist: numpy (~=1.17.4)
